mercylog_bashlog/__init__.py
mercylog_bashlog/bashlog-datalog.jar
mercylog_bashlog/bashlog.py
mercylog_bashlog/cli.py
mercylog_bashlog/config/__init__.py
mercylog_bashlog/config/config.py
mercylog_bashlog/lib/__init__.py
mercylog_bashlog/lib/util.py
mercylog_bashlog-0.2.0.dist-info/WHEEL
mercylog_bashlog-0.2.0.dist-info/METADATA
mercylog_bashlog-0.2.0.dist-info/RECORD
