Metadata-Version: 2.1
Name: mercylog-bashlog
Version: 0.2.0
Summary: Datalog(Bashlog) Inspired Logic Programming in Python
Author: Rajiv Abraham
Author-email: rajiv.abraham@gmail.com
Requires-Python: >=3.7,<4.0
Classifier: Programming Language :: Python :: 3
Classifier: Programming Language :: Python :: 3.7
Requires-Dist: click (>=7.0,<8.0)
